codenerix_products/__init__.py
codenerix_products/admin.py
codenerix_products/apps.py
codenerix_products/exceptions.py
codenerix_products/forms.py
codenerix_products/models.py
codenerix_products/tests.py
codenerix_products/urls.py
codenerix_products/views.py
codenerix_products/locale/en/LC_MESSAGES/django.po
codenerix_products/locale/es/LC_MESSAGES/django.mo
codenerix_products/locale/es/LC_MESSAGES/django.po
codenerix_products/migrations/0001_initial.py
codenerix_products/migrations/0002_auto_20180117_1628.py
codenerix_products/migrations/0003_auto_20180117_1655.py
codenerix_products/migrations/0004_auto_20180117_1745.py
codenerix_products/migrations/0005_auto_20180118_0739.py
codenerix_products/migrations/0006_auto_20180118_1126.py
codenerix_products/migrations/0007_auto_20180123_1316.py
codenerix_products/migrations/0007_product_caducable.py
codenerix_products/migrations/0008_auto_20180126_1711.py
codenerix_products/migrations/0009_auto_20180201_1137.py
codenerix_products/migrations/0010_merge_20180202_0726.py
codenerix_products/migrations/0011_auto_20180202_0826.py
codenerix_products/migrations/0012_productunique_caducity.py
codenerix_products/migrations/0013_alter_attribute_public_alter_brand_outstanding_and_more.py
codenerix_products/migrations/__init__.py
codenerix_products/migrations/__pycache__/0001_initial.cpython-310.pyc
codenerix_products/migrations/__pycache__/0001_initial.cpython-35.pyc
codenerix_products/migrations/__pycache__/0001_initial.cpython-39.pyc
codenerix_products/migrations/__pycache__/0002_auto_20180117_1628.cpython-310.pyc
codenerix_products/migrations/__pycache__/0002_auto_20180117_1628.cpython-35.pyc
codenerix_products/migrations/__pycache__/0002_auto_20180117_1628.cpython-39.pyc
codenerix_products/migrations/__pycache__/0003_auto_20180117_1655.cpython-310.pyc
codenerix_products/migrations/__pycache__/0003_auto_20180117_1655.cpython-35.pyc
codenerix_products/migrations/__pycache__/0003_auto_20180117_1655.cpython-39.pyc
django_codenerix_products-4.0.3.dist-info/LICENSE
django_codenerix_products-4.0.3.dist-info/METADATA
django_codenerix_products-4.0.3.dist-info/WHEEL
django_codenerix_products-4.0.3.dist-info/top_level.txt
django_codenerix_products-4.0.3.dist-info/RECORD
